
  [
    {
      "topicId": "B7",
    "questionText": "Explain the difference between hardware and software using examples.",
    "questionType": "theory",
    "marks": 5,
    "imageUrl": null
  },
  {
    "topicId": "B7",
    "questionText": "Study the diagram below showing parts of a system unit and explain the function of any two labelled components.",
    "questionType": "theory",
    "marks": 5,
    "imageUrl": "https://example.com/system-unit-diagram.png"
  },
  {
    "topicId": "B7",
    "questionText": "Describe the steps involved in booting a computer.",
    "questionType": "theory",
    "marks": 5,
    "imageUrl": null
  },
  {
    "topicId": "B7",
    "questionText": "Use the diagram below to explain the difference between input and output devices.",
    "questionType": "theory",
    "marks": 5,
    "imageUrl": "https://example.com/input-output-diagram.png"
  },
  {
    "topicId": "B7",
    "questionText": "Explain how to create, rename, and delete a folder on a computer.",
    "questionType": "theory",
    "marks": 5,
    "imageUrl": null
  },
  {
    "topicId": "B7",
    "questionText": "The image below shows a computer desktop. Identify any three features and explain their use.",
    "questionType": "theory",
    "marks": 5,
    "imageUrl": "https://example.com/desktop-features.png"
  },
  {
    "topicId": "B7",
    "questionText": "Using the diagram below, explain what a file path is and why it is important.",
    "questionType": "theory",
    "marks": 5,
    "imageUrl": "https://example.com/file-directory-tree.png"
  },
  {
    "topicId": "B7",
    "questionText": "Explain the process of copying and moving files using both keyboard shortcuts and the right-click method.",
    "questionType": "theory",
    "marks": 5,
    "imageUrl": null
  },
  {
    "topicId": "B7",
    "questionText": "The diagram shows icons commonly found on the desktop. Identify and explain the use of any two.",
    "questionType": "theory",
    "marks": 5,
    "imageUrl": "https://example.com/desktop-icons.png"
  },
  {
    "topicId": "B7",
    "questionText": "Explain the steps to safely shut down and restart a computer, and describe what happens during each process.",
    "questionType": "theory",
      "imageUrl": null
    }
  ]
  

